{
    "Branch_1":{
        "left":[
            1,
            2,
            3,
            4,
            7,
            8,
            9,
            10,
            11,
            12,
            13,
            14,
            15,
            16,
            17,
            18,
            19,
            20,
            23,
            24
        ],
        "left_volume":1529265,
        "right":[
            5,
            6,
            21,
            22,
            25,
            26,
            27,
            28,
            29,
            30
        ],
        "right_volume":339699
    },
    "Branch_10":{
        "left":[
            17,
            18
        ],
        "left_volume":38572,
        "right":[
            11,
            12
        ],
        "right_volume":252288
    },
    "Branch_11":{
        "left":[
            25,
            26
        ],
        "left_volume":36902,
        "right":[
            21,
            22
        ],
        "right_volume":40052
    },
    "Branch_12":{
        "left":[
            1,
            2
        ],
        "left_volume":307728,
        "right":[
            9,
            10
        ],
        "right_volume":206187
    },
    "Branch_13":{
        "left":[
            19,
            20
        ],
        "left_volume":214404,
        "right":[
            13,
            14
        ],
        "right_volume":60940
    },
    "Branch_14":{
        "left":[
            27,
            28
        ],
        "left_volume":73333,
        "right":[
            29,
            30
        ],
        "right_volume":140912
    },
    "Branch_15":{
        "left":[
            27
        ],
        "left_volume":36355,
        "right":[
            28
        ],
        "right_volume":36978
    },
    "Branch_16":{
        "left":[
            29
        ],
        "left_volume":69535,
        "right":[
            30
        ],
        "right_volume":71377
    },
    "Branch_17":{
        "left":[
            5
        ],
        "left_volume":23927,
        "right":[
            6
        ],
        "right_volume":24573
    },
    "Branch_18":{
        "left":[
            25
        ],
        "left_volume":18403,
        "right":[
            26
        ],
        "right_volume":18499
    },
    "Branch_19":{
        "left":[
            21
        ],
        "left_volume":20714,
        "right":[
            22
        ],
        "right_volume":19338
    },
    "Branch_2":{
        "left":[
            1,
            2,
            7,
            8,
            9,
            10,
            11,
            12,
            13,
            14,
            17,
            18,
            19,
            20
        ],
        "left_volume":1470676,
        "right":[
            3,
            4,
            15,
            16,
            23,
            24
        ],
        "right_volume":58589
    },
    "Branch_20":{
        "left":[
            19
        ],
        "left_volume":109971,
        "right":[
            20
        ],
        "right_volume":104433
    },
    "Branch_21":{
        "left":[
            13
        ],
        "left_volume":33473,
        "right":[
            14
        ],
        "right_volume":27467
    },
    "Branch_22":{
        "left":[
            17
        ],
        "left_volume":19995,
        "right":[
            18
        ],
        "right_volume":18577
    },
    "Branch_23":{
        "left":[
            11
        ],
        "left_volume":127844,
        "right":[
            12
        ],
        "right_volume":124444
    },
    "Branch_24":{
        "left":[
            7
        ],
        "left_volume":197823,
        "right":[
            8
        ],
        "right_volume":192734
    },
    "Branch_25":{
        "left":[
            1
        ],
        "left_volume":154557,
        "right":[
            2
        ],
        "right_volume":153171
    },
    "Branch_26":{
        "left":[
            9
        ],
        "left_volume":101551,
        "right":[
            10
        ],
        "right_volume":104636
    },
    "Branch_27":{
        "left":[
            3
        ],
        "left_volume":8970,
        "right":[
            4
        ],
        "right_volume":8724
    },
    "Branch_28":{
        "left":[
            15
        ],
        "left_volume":11888,
        "right":[
            16
        ],
        "right_volume":12167
    },
    "Branch_29":{
        "left":[
            23
        ],
        "left_volume":8331,
        "right":[
            24
        ],
        "right_volume":8509
    },
    "Branch_3":{
        "left":[
            3,
            4
        ],
        "left_volume":17694,
        "right":[
            15,
            16,
            23,
            24
        ],
        "right_volume":40895
    },
    "Branch_4":{
        "left":[
            13,
            14,
            19,
            20
        ],
        "left_volume":275344,
        "right":[
            1,
            2,
            7,
            8,
            9,
            10,
            11,
            12,
            17,
            18
        ],
        "right_volume":1195332
    },
    "Branch_5":{
        "left":[
            11,
            12,
            17,
            18
        ],
        "left_volume":290860,
        "right":[
            1,
            2,
            7,
            8,
            9,
            10
        ],
        "right_volume":904472
    },
    "Branch_6":{
        "left":[
            27,
            28,
            29,
            30
        ],
        "left_volume":214245,
        "right":[
            5,
            6,
            21,
            22,
            25,
            26
        ],
        "right_volume":125454
    },
    "Branch_7":{
        "left":[
            15,
            16
        ],
        "left_volume":24055,
        "right":[
            23,
            24
        ],
        "right_volume":16840
    },
    "Branch_8":{
        "left":[
            5,
            6
        ],
        "left_volume":48500,
        "right":[
            21,
            22,
            25,
            26
        ],
        "right_volume":76954
    },
    "Branch_9":{
        "left":[
            7,
            8
        ],
        "left_volume":390557,
        "right":[
            1,
            2,
            9,
            10
        ],
        "right_volume":513915
    }
}
